simple_calculator/__init__.py
simple_calculator/server.py
simple_mcp_calculator-0.1.0.dist-info/licenses/LICENSE
simple_mcp_calculator-0.1.0.dist-info/METADATA
simple_mcp_calculator-0.1.0.dist-info/WHEEL
simple_mcp_calculator-0.1.0.dist-info/entry_points.txt
simple_mcp_calculator-0.1.0.dist-info/top_level.txt
simple_mcp_calculator-0.1.0.dist-info/RECORD
