Metadata-Version: 2.4
Name: simple-mcp-calculator
Version: 0.1.0
Summary: MCP server that does simple mathematical ops
Author: Kavya-24
License: MIT
Classifier: Programming Language :: Python :: 3
Classifier: License :: OSI Approved :: MIT License
Classifier: Operating System :: OS Independent
Requires-Python: >=3.9
License-File: LICENSE
Requires-Dist: mcp>=1.2.0
Requires-Dist: requests
Requires-Dist: beautifulsoup4
Dynamic: license-file
